typer_demo_2022/__init__.py
typer_demo_2022/main.py
typer_demo_2022-1.0.1.dist-info/entry_points.txt
typer_demo_2022-1.0.1.dist-info/LICENSE
typer_demo_2022-1.0.1.dist-info/WHEEL
typer_demo_2022-1.0.1.dist-info/METADATA
typer_demo_2022-1.0.1.dist-info/RECORD
