Metadata-Version: 2.1
Name: typer-demo-2022
Version: 1.0.1
Summary: Demo de typer para gulag
License: GPL v3
Author: Alex Pineda
Author-email: alejandro.deathscythe@google.com
Requires-Python: >=3.9,<4.0
Classifier: License :: Other/Proprietary License
Classifier: Programming Language :: Python :: 3
Classifier: Programming Language :: Python :: 3.10
Classifier: Programming Language :: Python :: 3.9
Requires-Dist: typer (>=0.4.0,<0.5.0)
